{"RIGHT_ASCENSION_DEG":225.686732,"DECLINATION_DEG":-3.0314874,"PLANET_EQ_TEMPERATURE_K":3353.0,"STAR_METALLICITY_DEX":0.29,"DISCOVERY_METHOD":"Transit","CONTROVERSIAL_FLAG":0.0,"ORBITAL_AXIS_LIMIT":0.0}
{"RIGHT_ASCENSION_DEG":292.24719,"DECLINATION_DEG":47.9695429,"PLANET_EQ_TEMPERATURE_K":2733.0,"STAR_METALLICITY_DEX":0.26,"DISCOVERY_METHOD":"Transit","CONTROVERSIAL_FLAG":0.0,"ORBITAL_AXIS_LIMIT":0.0}
{"RIGHT_ASCENSION_DEG":107.6002312,"DECLINATION_DEG":-39.0972705,"PLANET_EQ_TEMPERATURE_K":2720.0,"STAR_METALLICITY_DEX":0.13,"DISCOVERY_METHOD":"Transit","CONTROVERSIAL_FLAG":0.0,"ORBITAL_AXIS_LIMIT":0.0}
{"RIGHT_ASCENSION_DEG":247.6669998,"DECLINATION_DEG":49.0467891,"PLANET_EQ_TEMPERATURE_K":2609.0,"STAR_METALLICITY_DEX":0.22,"DISCOVERY_METHOD":"Transit","CONTROVERSIAL_FLAG":0.0,"ORBITAL_AXIS_LIMIT":0.0}
{"RIGHT_ASCENSION_DEG":97.636645,"DECLINATION_DEG":29.6722662,"PLANET_EQ_TEMPERATURE_K":2601.0,"STAR_METALLICITY_DEX":0.12,"DISCOVERY_METHOD":"Transit","CONTROVERSIAL_FLAG":0.0,"ORBITAL_AXIS_LIMIT":0.0}
{"RIGHT_ASCENSION_DEG":317.5515264,"DECLINATION_DEG":10.7388967,"PLANET_EQ_TEMPERATURE_K":2594.3,"STAR_METALLICITY_DEX":0.15,"DISCOVERY_METHOD":"Transit","CONTROVERSIAL_FLAG":0.0,"ORBITAL_AXIS_LIMIT":0.0}
{"RIGHT_ASCENSION_DEG":286.9713876,"DECLINATION_DEG":46.8682463,"PLANET_EQ_TEMPERATURE_K":2550.0,"STAR_METALLICITY_DEX":0.2,"DISCOVERY_METHOD":"Transit","CONTROVERSIAL_FLAG":0.0,"ORBITAL_AXIS_LIMIT":0.0}
{"RIGHT_ASCENSION_DEG":227.270329,"DECLINATION_DEG":-42.7049658,"PLANET_EQ_TEMPERATURE_K":2470.0,"STAR_METALLICITY_DEX":0.21,"DISCOVERY_METHOD":"Transit","CONTROVERSIAL_FLAG":0.0,"ORBITAL_AXIS_LIMIT":0.0}
{"RIGHT_ASCENSION_DEG":140.3390845,"DECLINATION_DEG":14.3678691,"PLANET_EQ_TEMPERATURE_K":2463.0,"STAR_METALLICITY_DEX":0.255,"DISCOVERY_METHOD":"Transit","CONTROVERSIAL_FLAG":0.0,"ORBITAL_AXIS_LIMIT":0.0}
{"RIGHT_ASCENSION_DEG":24.3544618,"DECLINATION_DEG":-45.6777937,"PLANET_EQ_TEMPERATURE_K":2429.0,"STAR_METALLICITY_DEX":0.107,"DISCOVERY_METHOD":"Transit","CONTROVERSIAL_FLAG":0.0,"ORBITAL_AXIS_LIMIT":0.0}
